{
  "version": "7",
  "dialect": "sqlite",
  "entries": [
    {
      "idx": 0,
      "version": "6",
      "when": 1769321875293,
      "tag": "0000_swift_spirit",
      "breakpoints": true
    },
    {
      "idx": 1,
      "version": "6",
      "when": 1769324875818,
      "tag": "0001_acoustic_gunslinger",
      "breakpoints": true
    },
    {
      "idx": 2,
      "version": "6",
      "when": 1769346752108,
      "tag": "0002_nasty_star_brand",
      "breakpoints": true
    },
    {
      "idx": 3,
      "version": "6",
      "when": 1769351877760,
      "tag": "0003_flimsy_darkstar",
      "breakpoints": true
    },
    {
      "idx": 4,
      "version": "6",
      "when": 1769454619316,
      "tag": "0004_funny_tag",
      "breakpoints": true
    },
    {
      "idx": 5,
      "version": "6",
      "when": 1769557997850,
      "tag": "0005_confused_lord_tyger",
      "breakpoints": true
    },
    {
      "idx": 6,
      "version": "6",
      "when": 1769562765623,
      "tag": "0006_perfect_dragon_man",
      "breakpoints": true
    },
    {
      "idx": 7,
      "version": "6",
      "when": 1769752500000,
      "tag": "0007_hushed_lightspeed",
      "breakpoints": true
    },
    {
      "idx": 8,
      "version": "6",
      "when": 1770157265187,
      "tag": "0008_special_adam_destine",
      "breakpoints": true
    },
    {
      "idx": 9,
      "version": "6",
      "when": 1770175236347,
      "tag": "0009_steady_shen",
      "breakpoints": true
    },
    {
      "idx": 10,
      "version": "6",
      "when": 1770176143662,
      "tag": "0010_daffy_vertigo",
      "breakpoints": true
    }
  ]
}